csvcubeddevtools/__init__.py
csvcubeddevtools/behaviour/__init__.py
csvcubeddevtools/behaviour/csv2rdf.py
csvcubeddevtools/behaviour/csvlint.py
csvcubeddevtools/behaviour/dockerornot.py
csvcubeddevtools/behaviour/environment.py
csvcubeddevtools/behaviour/file.py
csvcubeddevtools/behaviour/rdf.py
csvcubeddevtools/behaviour/sparqltests.py
csvcubeddevtools/behaviour/temporarydirectory.py
csvcubeddevtools/helpers/__init__.py
csvcubeddevtools/helpers/csvwhelpers.py
csvcubeddevtools/helpers/file.py
csvcubeddevtools/helpers/rdflibhelpers.py
csvcubeddevtools/helpers/shell.py
csvcubeddevtools/helpers/tar.py
csvcubed_devtools-0.2.0.dist-info/LICENSE
csvcubed_devtools-0.2.0.dist-info/METADATA
csvcubed_devtools-0.2.0.dist-info/WHEEL
csvcubed_devtools-0.2.0.dist-info/RECORD
