Metadata-Version: 2.1
Name: csvcubed-devtools
Version: 0.2.0
Summary: Development tools and dependencies for use in the csvcubed tooling.
License: Apache-2.0
Author: Integrated Data Service - Dissemination
Author-email: csvcubed@gsscogs.uk
Requires-Python: >=3.9,<4.0
Classifier: License :: OSI Approved :: Apache Software License
Classifier: Programming Language :: Python :: 3
Classifier: Programming Language :: Python :: 3.9
Classifier: Programming Language :: Python :: 3.10
Classifier: Programming Language :: Python :: 3.11
Requires-Dist: Jinja2 (>=3.1.2,<4.0.0)
Requires-Dist: behave
Requires-Dist: black
Requires-Dist: chardet
Requires-Dist: csvw
Requires-Dist: docker
Requires-Dist: pytest
Requires-Dist: python-dateutil
Requires-Dist: pywin32 (>=301) ; sys_platform == "win32"
Requires-Dist: rdflib (>=6.0.0)
